yamlize/__init__.py
yamlize/attribute_collection.py
yamlize/attributes.py
yamlize/maps.py
yamlize/objects.py
yamlize/round_trip_data.py
yamlize/sequences.py
yamlize/yamlizable.py
yamlize/yamlizing_error.py
yamlize/tests/__init__.py
yamlize/tests/test_data_validation.py
yamlize/tests/test_inheritance.py
yamlize/tests/test_maps.py
yamlize/tests/test_sequence.py
yamlize/tests/test_yamlizable.py
yamlize-0.7.1.dist-info/LICENSE
yamlize-0.7.1.dist-info/METADATA
yamlize-0.7.1.dist-info/WHEEL
yamlize-0.7.1.dist-info/top_level.txt
yamlize-0.7.1.dist-info/RECORD
